README.rst
setup.py
z0bug_odoo/LICENSE
z0bug_odoo/__init__.py
z0bug_odoo/__main__.py
z0bug_odoo/_check4deps_.py
z0bug_odoo/test_common.py
z0bug_odoo/test_pycharm_unicode.py
z0bug_odoo/z0bug_odoo_lib.py
z0bug_odoo.egg-info/PKG-INFO
z0bug_odoo.egg-info/SOURCES.txt
z0bug_odoo.egg-info/dependency_links.txt
z0bug_odoo.egg-info/entry_points.txt
z0bug_odoo.egg-info/not-zip-safe
z0bug_odoo.egg-info/requires.txt
z0bug_odoo.egg-info/top_level.txt
z0bug_odoo/data/account_account.xlsx
z0bug_odoo/data/account_banking_mandate.xlsx
z0bug_odoo/data/account_fiscal_position.xlsx
z0bug_odoo/data/account_fiscal_position_tax.xlsx
z0bug_odoo/data/account_fiscal_year.xlsx
z0bug_odoo/data/account_invoice.xlsx
z0bug_odoo/data/account_invoice_line.xlsx
z0bug_odoo/data/account_journal.xlsx
z0bug_odoo/data/account_move.xlsx
z0bug_odoo/data/account_move_line.xlsx
z0bug_odoo/data/account_payment_method.xlsx
z0bug_odoo/data/account_payment_mode.xlsx
z0bug_odoo/data/account_payment_term.xlsx
z0bug_odoo/data/account_payment_term_line.xlsx
z0bug_odoo/data/account_rc_type.xlsx
z0bug_odoo/data/account_rc_type_tax.xlsx
z0bug_odoo/data/account_tax.xlsx
z0bug_odoo/data/asset_asset.xlsx
z0bug_odoo/data/asset_category.xlsx
z0bug_odoo/data/asset_category_depreciation_type.xlsx
z0bug_odoo/data/base.partner_admin.png
z0bug_odoo/data/date_range.xlsx
z0bug_odoo/data/date_range_type.xlsx
z0bug_odoo/data/decimal_precision.xlsx
z0bug_odoo/data/dichiarazione_intento.xlsx
z0bug_odoo/data/dichiarazione_intento_yearly_limit.xlsx
z0bug_odoo/data/italy_profile_account.xlsx
z0bug_odoo/data/miscellaneous.xlsx
z0bug_odoo/data/modules.xlsx
z0bug_odoo/data/product_product.xlsx
z0bug_odoo/data/product_supplierinfo.xlsx
z0bug_odoo/data/product_template.xlsx
z0bug_odoo/data/purchase_order.xlsx
z0bug_odoo/data/purchase_order_line.xlsx
z0bug_odoo/data/res_bank.xlsx
z0bug_odoo/data/res_company.xlsx
z0bug_odoo/data/res_country_state.xlsx
z0bug_odoo/data/res_currency_rate.xlsx
z0bug_odoo/data/res_partner.xlsx
z0bug_odoo/data/res_partner_bank.xlsx
z0bug_odoo/data/sale_order.xlsx
z0bug_odoo/data/sale_order_line.xlsx
z0bug_odoo/data/stock_inventory.xlsx
z0bug_odoo/data/stock_inventory_line.xlsx
z0bug_odoo/data/withholding_tax.xlsx
z0bug_odoo/egg-info/CHANGELOG.rst
z0bug_odoo/egg-info/DESCRIPTION.rst
z0bug_odoo/egg-info/FEATURES.rst
z0bug_odoo/egg-info/INSTALLATION.rst
z0bug_odoo/egg-info/USAGE.rst
z0bug_odoo/egg-info/description_qci.csv
z0bug_odoo/egg-info/description_qci_partner.csv
z0bug_odoo/egg-info/flake8_error.csv
z0bug_odoo/egg-info/level_summary.csv
z0bug_odoo/egg-info/pylint_error.csv
z0bug_odoo/egg-info/test_level.csv
z0bug_odoo/egg-info/testenv_description.rst
z0bug_odoo/egg-info/testenv_template.rst
z0bug_odoo/egg-info/testenv_usage.rst
z0bug_odoo/egg-info/testenv_usage_data_2many.rst
z0bug_odoo/egg-info/testenv_usage_data_binary.rst
z0bug_odoo/egg-info/testenv_usage_data_boolean.rst
z0bug_odoo/egg-info/testenv_usage_data_char.rst
z0bug_odoo/egg-info/testenv_usage_data_company_id.rst
z0bug_odoo/egg-info/testenv_usage_data_currency_id.rst
z0bug_odoo/egg-info/testenv_usage_data_datetime.rst
z0bug_odoo/egg-info/testenv_usage_data_many2one.rst
z0bug_odoo/egg-info/testenv_usage_data_numeric.rst
z0bug_odoo/egg-info/testenv_usage_data_values.rst
z0bug_odoo/egg-info/testenv_usage_execution_session.rst
z0bug_odoo/egg-info/testenv_usage_expr.csv
z0bug_odoo/egg-info/testenv_usage_external_reference.rst
z0bug_odoo/egg-info/testenv_usage_functions.rst
z0bug_odoo/egg-info/testenv_usage_magic_relationship.rst
z0bug_odoo/egg-info/testenv_usage_model_data_declaration.rst
z0bug_odoo/egg-info/testenv_useful_external_reference.csv
z0bug_odoo/egg-info/variables.csv
