Metadata-Version: 1.2
Name: z0bug-odoo
Version: 2.0.23
Summary: Odoo testing framework
Home-page: https://github.com/zeroincombenze/tools
Author: Antonio Maria Vigliotti
Author-email: antoniomaria.vigliotti@gmail.com
License: GPL-3.0-or-later
Project-URL: Source, https://github.com/zeroincombenze/tools/tree/master/z0bug_odoo
Project-URL: Documentation, https://zeroincombenze-tools.readthedocs.io/en/latest/z0bug_odoo
Project-URL: Changelog, https://github.com/zeroincombenze/tools/blob/master/z0bug_odoo/egg-info/CHANGELOG.rst
Keywords: unit test debug
Platform: UNKNOWN
Classifier: Development Status :: 4 - Beta
Classifier: Operating System :: POSIX
Classifier: Programming Language :: Python :: 2.7
Classifier: Programming Language :: Python :: 3.7
Classifier: Programming Language :: Python :: 3.8
Classifier: Programming Language :: Python :: 3.9
Classifier: Programming Language :: Python :: 3.10
Classifier: Programming Language :: Python :: 3.11
Classifier: Programming Language :: Python :: 3.12
Classifier: Intended Audience :: Developers
Classifier: Topic :: Software Development
Classifier: Topic :: Software Development :: Libraries
Classifier: Topic :: System :: System Shells
